errify/__init__.py
errify/errify.py
errify-0.1.0.dist-info/METADATA
errify-0.1.0.dist-info/WHEEL
errify-0.1.0.dist-info/entry_points.txt
errify-0.1.0.dist-info/top_level.txt
errify-0.1.0.dist-info/RECORD
