Metadata-Version: 2.4
Name: errify
Version: 0.1.0
Summary: Human-readable error messages for Python beginners
Home-page: https://github.com/DivakarBabuMP/errify
Author: Divakar Babu M P
Author-email: divakarbabu369@gmail.com
Project-URL: Bug Reports, https://github.com/DivakarBabuMP/errify/issues
Project-URL: Source, https://github.com/DivakarBabuMP/errify
Keywords: error-handling education debugging beginner-friendly
Classifier: Development Status :: 3 - Alpha
Classifier: Intended Audience :: Education
Classifier: Intended Audience :: Developers
Classifier: Topic :: Software Development :: Libraries :: Python Modules
Classifier: Topic :: Education
Classifier: License :: OSI Approved :: MIT License
Classifier: Programming Language :: Python :: 3
Classifier: Programming Language :: Python :: 3.7
Classifier: Programming Language :: Python :: 3.8
Classifier: Programming Language :: Python :: 3.9
Classifier: Programming Language :: Python :: 3.10
Classifier: Programming Language :: Python :: 3.11
Requires-Python: >=3.7
Dynamic: author
Dynamic: author-email
Dynamic: classifier
Dynamic: description
Dynamic: description-content-type
Dynamic: home-page
Dynamic: keywords
Dynamic: project-url
Dynamic: requires-python
Dynamic: summary
